pyhubio.py
pyhubio-1.4.dist-info/LICENSE
pyhubio-1.4.dist-info/METADATA
pyhubio-1.4.dist-info/WHEEL
pyhubio-1.4.dist-info/top_level.txt
pyhubio-1.4.dist-info/RECORD
