Metadata-Version: 2.1
Name: pyhubio
Version: 1.4
Summary: A small library to communicate with AXI4 and AXI4-Stream hubs
Author: Pavel Demin
License: MIT
Project-URL: Homepage, https://github.com/pavel-demin/pyhubio
Requires-Python: >=3.8
License-File: LICENSE
Requires-Dist: libusb1
Requires-Dist: numpy
